audiogrep/__init__.py
audiogrep/audiogrep.py
audiogrep-0.1.5.data/scripts/audiogrep
audiogrep-0.1.5.dist-info/DESCRIPTION.rst
audiogrep-0.1.5.dist-info/METADATA
audiogrep-0.1.5.dist-info/RECORD
audiogrep-0.1.5.dist-info/WHEEL
audiogrep-0.1.5.dist-info/metadata.json
audiogrep-0.1.5.dist-info/top_level.txt
