Metadata-Version: 2.0
Name: audiogrep
Version: 0.1.5
Summary: Creates audio supercuts
Home-page: http://antiboredom.github.io/audiogrep
Author: Sam Lavigne
Author-email: splavigne@gmail.com
License: LICENSE
Keywords: audio supercut pydub transcribe transcription
Platform: UNKNOWN
Classifier: Development Status :: 4 - Beta
Classifier: Topic :: Multimedia :: Sound/Audio
Classifier: Topic :: Multimedia :: Sound/Audio :: Editors
Classifier: Topic :: Multimedia :: Sound/Audio :: Speech
Requires-Dist: pydub
